{
  "unversionedId": "tutorials/first-analytic-app",
  "id": "tutorials/first-analytic-app",
  "isDocsHomePage": false,
  "title": "How to Build Your First Analytic Application Using Qrvey Composer",
  "description": "window.addEventListener(\"load\",() =&gt; {\"{\"}",
  "source": "@site/../docs/tutorials/first-analytic-app.md",
  "slug": "/tutorials/first-analytic-app",
  "permalink": "/docs/next/tutorials/first-analytic-app",
  "version": "current",
  "lastUpdatedBy": "Domingo Sanchez",
  "lastUpdatedAt": 1620070468,
  "formattedLastUpdatedAt": "5/3/2021",
  "sidebar_label": "Your First Analytic Application",
  "sidebar": "tutorials",
  "next": {
    "title": "How to Create a Chart in Qrvey Composer",
    "permalink": "/docs/next/tutorials/create-charts"
  }
}